ap_scanner.py
CHANGELOG.txt
scanner.py
utils.py
ap_scanner-0.1.2.dist-info/entry_points.txt
ap_scanner-0.1.2.dist-info/LICENSE
ap_scanner-0.1.2.dist-info/METADATA
ap_scanner-0.1.2.dist-info/WHEEL
ap_scanner-0.1.2.dist-info/RECORD
