Metadata-Version: 2.1
Name: ap_scanner
Version: 0.1.2
Summary: Wifi AP scanner tool
Author: JavaWiz
Author-email: JavaWiz1@hotmail.com
Requires-Python: >=3.7,<4.0
Classifier: Programming Language :: Python :: 3
Classifier: Programming Language :: Python :: 3.7
Classifier: Programming Language :: Python :: 3.8
Classifier: Programming Language :: Python :: 3.9
Classifier: Programming Language :: Python :: 3.10
Classifier: Programming Language :: Python :: 3.11
Requires-Dist: loguru (>=0.7,<0.8)
